search/__init__.py
search/utils.py
example_search_balancy_0.9-0.9.dist-info/LICENSE.txt
example_search_balancy_0.9-0.9.dist-info/METADATA
example_search_balancy_0.9-0.9.dist-info/WHEEL
example_search_balancy_0.9-0.9.dist-info/top_level.txt
example_search_balancy_0.9-0.9.dist-info/RECORD
