Metadata-Version: 2.1
Name: example-search-balancy-0.9
Version: 0.9
Summary: UNKNOWN
Home-page: UNKNOWN
Author: balancy
Author-email: balancy@gmail.com
License: UNKNOWN
Platform: UNKNOWN
Requires-Dist: beautifulsoup4
Requires-Dist: lxml
Requires-Dist: requests
Requires-Dist: terminaltables
